git_pijul.py
git_pijul-0.9.2.dist-info/entry_points.txt
git_pijul-0.9.2.dist-info/LICENSE
git_pijul-0.9.2.dist-info/WHEEL
git_pijul-0.9.2.dist-info/METADATA
git_pijul-0.9.2.dist-info/RECORD
