Metadata-Version: 2.1
Name: git-pijul
Version: 0.9.2
Summary: update pijul from git
Home-page: https://github.com/ganwell/git-pijul
License: AGPL-3.0-or-later
Author: Jean-Louis Fuchs
Author-email: jean-louis.fuchs@adfinis-sygroup.ch
Requires-Python: >=3.9,<4.0
Classifier: License :: OSI Approved :: GNU Affero General Public License v3 or later (AGPLv3+)
Classifier: Programming Language :: Python :: 3
Classifier: Programming Language :: Python :: 3.9
Classifier: Topic :: Software Development :: Version Control
Requires-Dist: click (>=8.0.1)
Requires-Dist: temppathlib (>=1.1.0)
Requires-Dist: toml (>=0.10.2)
Requires-Dist: tqdm (>=4.61.2)
Project-URL: Repository, https://github.com/ganwell/git-pijul
